MANIFEST.in
setup.cfg
setup.py
stracks_api/__init__.py
stracks_api/api.py
stracks_api/client.py
stracks_api/connector.py
stracks_api/levels.py
stracks_api/middleware.py
stracks_api/tasks.py
stracks_api/util.py
stracks_api.egg-info/PKG-INFO
stracks_api.egg-info/SOURCES.txt
stracks_api.egg-info/dependency_links.txt
stracks_api.egg-info/entry_points.txt
stracks_api.egg-info/not-zip-safe
stracks_api.egg-info/requires.txt
stracks_api.egg-info/top_level.txt
stracks_api/tests/__init__.py
stracks_api/tests/base.py
stracks_api/tests/test_action.py
stracks_api/tests/test_api.py
stracks_api/tests/test_client.py
stracks_api/tests/test_connector_multiplex.py
stracks_api/tests/test_entity.py