Metadata-Version: 1.0
Name: stracks-api
Version: 0.2dev
Summary: API for Stracks service
Home-page: http://github.com/Stracksapp/stracks_api
Author: Ivo van der Wijk
Author-email: stracks-api@in.m3r.nl
License: UNKNOWN
Platform: UNKNOWN
